odoo/addons/purchase_analytic/README.rst
odoo/addons/purchase_analytic/__init__.py
odoo/addons/purchase_analytic/__manifest__.py
odoo/addons/purchase_analytic/i18n/es.po
odoo/addons/purchase_analytic/i18n/fr.po
odoo/addons/purchase_analytic/i18n/hr.po
odoo/addons/purchase_analytic/i18n/it.po
odoo/addons/purchase_analytic/i18n/pt_BR.po
odoo/addons/purchase_analytic/i18n/purchase_analytic.pot
odoo/addons/purchase_analytic/i18n/tr.po
odoo/addons/purchase_analytic/models/__init__.py
odoo/addons/purchase_analytic/models/purchase.py
odoo/addons/purchase_analytic/readme/CONTRIBUTORS.md
odoo/addons/purchase_analytic/readme/DESCRIPTION.md
odoo/addons/purchase_analytic/readme/HISTORY.md
odoo/addons/purchase_analytic/static/description/icon.png
odoo/addons/purchase_analytic/static/description/index.html
odoo/addons/purchase_analytic/tests/__init__.py
odoo/addons/purchase_analytic/tests/test_purchase_analytic.py
odoo/addons/purchase_analytic/views/purchase_views.xml
odoo_addon_purchase_analytic-18.0.1.0.0.11.dist-info/METADATA
odoo_addon_purchase_analytic-18.0.1.0.0.11.dist-info/WHEEL
odoo_addon_purchase_analytic-18.0.1.0.0.11.dist-info/top_level.txt
odoo_addon_purchase_analytic-18.0.1.0.0.11.dist-info/RECORD
